tree_sitter_languages-stubs/METADATA.toml
tree_sitter_languages-stubs/__init__.pyi
tree_sitter_languages-stubs/core.pyi
tree_sitter_languages-stubs/py.typed
types_tree_sitter_languages-1.10.0.20250319.dist-info/LICENSE
types_tree_sitter_languages-1.10.0.20250319.dist-info/METADATA
types_tree_sitter_languages-1.10.0.20250319.dist-info/WHEEL
types_tree_sitter_languages-1.10.0.20250319.dist-info/top_level.txt
types_tree_sitter_languages-1.10.0.20250319.dist-info/RECORD
